easy_kclpy/__init__.py
easy_kclpy/kinesis_processor.py
easy_kclpy/version.py
easy_kclpy/utils/__init__.py
easy_kclpy/utils/generate_kcl_properties_file_from_env.py
easy_kclpy/utils/kinesis_to_file_processor.py
easy_kclpy/utils/launch_multilangdaemon.py
easy_kclpy-2021.7.2.dist-info/LICENSE.txt
easy_kclpy-2021.7.2.dist-info/METADATA
easy_kclpy-2021.7.2.dist-info/NOTICE.txt
easy_kclpy-2021.7.2.dist-info/WHEEL
easy_kclpy-2021.7.2.dist-info/top_level.txt
easy_kclpy-2021.7.2.dist-info/RECORD
